py4cst/__init__.py
py4cst/cst_file_utils.py
py4cst/farfield_utils.py
py4cst/ffplot.py
py4cst/ffs.py
py4cst/installation_util.py
py4cst/material_library.py
py4cst/material_utils.py
py4cst/matrix_conversions.py
py4cst/mesh_utils.py
py4cst/parameter_sweep.py
py4cst/py.typed
py4cst/CST/__init__.py
py4cst/CST/frequency_range_list.py
py4cst/CST/history_list_generator.py
py4cst/CST/ihistory_list_provider.py
py4cst/CST/interface.py
py4cst/CST/interface_pcbs.py
py4cst/CST/iproject.py
py4cst/CST/iquiet_mode_controller.py
py4cst/CST/ivba_provider.py
py4cst/CST/ivba_runtime.py
py4cst/CST/modeler.py
py4cst/CST/parameters.py
py4cst/CST/project.py
py4cst/CST/result_item.py
py4cst/CST/result_module.py
py4cst/CST/results.py
py4cst/CST/schematic.py
py4cst/CST/units.py
py4cst/CST/vba_obj_wrapper.py
py4cst/CST/vba_type_name.py
py4cst/CST/wrappers/__init__.py
py4cst/CST/wrappers/ads_cosimulation.py
py4cst/CST/wrappers/align.py
py4cst/CST/wrappers/analytical_curve.py
py4cst/CST/wrappers/analytical_face.py
py4cst/CST/wrappers/anchorpoint.py
py4cst/CST/wrappers/arc.py
py4cst/CST/wrappers/asymptotic_solver.py
py4cst/CST/wrappers/background.py
py4cst/CST/wrappers/boundary.py
py4cst/CST/wrappers/brick.py
py4cst/CST/wrappers/component.py
py4cst/CST/wrappers/cone.py
py4cst/CST/wrappers/curve.py
py4cst/CST/wrappers/cylinder.py
py4cst/CST/wrappers/discrete_face_port.py
py4cst/CST/wrappers/discrete_port.py
py4cst/CST/wrappers/eigenmode_solver.py
py4cst/CST/wrappers/elliptical_cylinder.py
py4cst/CST/wrappers/extrude.py
py4cst/CST/wrappers/farfield_plot.py
py4cst/CST/wrappers/farfield_source.py
py4cst/CST/wrappers/fd_solver.py
py4cst/CST/wrappers/field_source.py
py4cst/CST/wrappers/floquet_port.py
py4cst/CST/wrappers/group.py
py4cst/CST/wrappers/hf_solver.py
py4cst/CST/wrappers/ie_solver.py
py4cst/CST/wrappers/layer_stacking.py
py4cst/CST/wrappers/loft.py
py4cst/CST/wrappers/lumped_element.py
py4cst/CST/wrappers/lumped_face_element.py
py4cst/CST/wrappers/material.py
py4cst/CST/wrappers/mesh.py
py4cst-0.2.0.dist-info/licenses/LICENSE
py4cst-0.2.0.dist-info/METADATA
py4cst-0.2.0.dist-info/WHEEL
py4cst-0.2.0.dist-info/top_level.txt
py4cst-0.2.0.dist-info/RECORD
