Metadata-Version: 2.4
Name: py4cst
Version: 0.2.0
Summary: Automation/Scripting library for CST Studio Suite
Author: Samuel Travnicek
License: MIT License
Project-URL: Homepage, https://github.com/Arri0/py4cst
Project-URL: Repository, https://github.com/Arri0/py4cst
Keywords: CST Studio Suite,Automation,Electromagnetic Field,Simulation
Classifier: Development Status :: 4 - Beta
Classifier: Intended Audience :: Developers
Classifier: Programming Language :: Python :: 3
Classifier: Programming Language :: Python :: 3.9
Classifier: Programming Language :: Python :: 3.10
Classifier: Programming Language :: Python :: 3.11
Classifier: Operating System :: POSIX :: Linux
Classifier: Operating System :: Microsoft :: Windows
Requires-Python: >=3.9
License-File: LICENSE
Requires-Dist: numpy
Requires-Dist: parse
Requires-Dist: matplotlib
Provides-Extra: dev
Requires-Dist: pyyaml; extra == "dev"
Dynamic: license-file
